README.txt
buildout.cfg
setup.py
src/zif/__init__.py
src/zif.headincludes.egg-info/PKG-INFO
src/zif.headincludes.egg-info/SOURCES.txt
src/zif.headincludes.egg-info/dependency_links.txt
src/zif.headincludes.egg-info/namespace_packages.txt
src/zif.headincludes.egg-info/not-zip-safe
src/zif.headincludes.egg-info/requires.txt
src/zif.headincludes.egg-info/top_level.txt
src/zif/headincludes/LICENSE.txt
src/zif/headincludes/README.txt
src/zif/headincludes/__init__.py
src/zif/headincludes/configure.zcml
src/zif/headincludes/headinclude.py
src/zif/headincludes/headincluder.py
src/zif/headincludes/interfaces.py
src/zif/headincludes/meta.zcml
src/zif/headincludes/queues.py
src/zif/headincludes/resourcelibrary.py
src/zif/headincludes/tal.py
src/zif/headincludes/tests.py
src/zif/headincludes/zcml.py
src/zif/headincludes/zif.headincludes-configure.zcml
src/zif/headincludes/zif.headincludes-meta.zcml