Metadata-Version: 1.0
Name: zif.headincludes
Version: 0.4
Summary: WSGI middleware to manipulate css and javascript in the HTML header.
Home-page: http://zif.svn.sourceforge.net/viewvc/zif/zif.headincludes
Author: Jim Washington and contributors
Author-email: jwashin@users.sourceforge.net
License: BSD
Keywords: headincludes wsgi middleware zope3
Platform: UNKNOWN
Classifier: Framework :: Buildout
Classifier: Framework :: Zope3
Classifier: Intended Audience :: Developers
Classifier: Development Status :: 5 - Production/Stable
Classifier: Environment :: Web Environment
Classifier: License :: OSI Approved :: BSD License
Classifier: Operating System :: OS Independent
Classifier: Programming Language :: Python
Classifier: Topic :: Software Development :: Libraries :: Python Modules
